h1s/__init__.py
h1s/addTaxa1s.py
h1s/addTaxon1s.py
h1s/checkData1s.py
h1s/merge1sOutput.py
h1s/remove1s.py
h1s/runOneseq.py
h1s/setup1s.py
h1s/bin/Filehandler.pm
h1s/bin/__init__.py
h1s/bin/hamstr.pl
h1s/bin/oneSeq.pl
h1s/bin/run_genewise_hamstr.pm
h1s/bin/translate.pl
h1s/data/__init__.py
h1s/data/infile.fa
h1s/setup/__init__.py
h1s/setup/indexTaxonomy.pl
h1s/setup/install_lib.sh
h1s/setup/setup.sh
h1s/setup/setup_conda.sh
hamstr1s/__init__.py
hamstr1s/addTaxa1s.py
hamstr1s/addTaxaHamstr.py
hamstr1s/addTaxon1s.py
hamstr1s/addTaxonHamstr.py
hamstr1s/checkData1s.py
hamstr1s/checkDataHamstr.py
hamstr1s/merge1sOutput.py
hamstr1s/mergePhyloprofileData.py
hamstr1s/remove1s.py
hamstr1s/runOneseq.py
hamstr1s/setup1s.py
hamstr1s/setupOneseq.py
hamstr1s/bin/Filehandler.pm
hamstr1s/bin/__init__.py
hamstr1s/bin/hamstr.pl
hamstr1s/bin/oneSeq.pl
hamstr1s/bin/run_genewise_hamstr.pm
hamstr1s/bin/translate.pl
hamstr1s/data/__init__.py
hamstr1s/data/infile.fa
hamstr1s/setup/__init__.py
hamstr1s/setup/indexTaxonomy.pl
hamstr1s/setup/install_lib.sh
hamstr1s/setup/setup.sh
hamstr1s/setup/setup_conda.sh
h1s-2.1.2.dist-info/LICENCE
h1s-2.1.2.dist-info/METADATA
h1s-2.1.2.dist-info/WHEEL
h1s-2.1.2.dist-info/entry_points.txt
h1s-2.1.2.dist-info/top_level.txt
h1s-2.1.2.dist-info/RECORD
