Metadata-Version: 2.1
Name: h1s
Version: 2.1.2
Summary: Feature-aware orthology prediction tool
Home-page: https://github.com/BIONF/HaMStR
Author: Vinh Tran
Author-email: tran@bio.uni-frankfurt.de
License: GPL-3.0
Platform: UNKNOWN
Classifier: Environment :: Console
Classifier: Intended Audience :: End Users/Desktop
Classifier: License :: OSI Approved :: GNU General Public License v3 or later (GPLv3+)
Classifier: Natural Language :: English
Classifier: Programming Language :: Python :: 3
Requires-Python: >=3.7.0
Requires-Dist: biopython
Requires-Dist: tqdm
Requires-Dist: ete3
Requires-Dist: six
Requires-Dist: greedyFAS
